jeff/__init__.py
jeff/capnp.py
jeff/py.typed
jeff/data/jeff.capnp
jeff_format-0.1.0.dev0.dist-info/METADATA
jeff_format-0.1.0.dev0.dist-info/WHEEL
jeff_format-0.1.0.dev0.dist-info/licenses/LICENCE
jeff_format-0.1.0.dev0.dist-info/RECORD
